rockgarden/__init__.py
rockgarden/assets.py
rockgarden/cli.py
rockgarden/config.py
rockgarden/links.py
rockgarden/urls.py
rockgarden/content/__init__.py
rockgarden/content/loader.py
rockgarden/content/models.py
rockgarden/content/store.py
rockgarden/content/strip_title.py
rockgarden/nav/__init__.py
rockgarden/nav/breadcrumbs.py
rockgarden/nav/folder_index.py
rockgarden/nav/labels.py
rockgarden/nav/tree.py
rockgarden/obsidian/__init__.py
rockgarden/obsidian/embeds.py
rockgarden/obsidian/wikilinks.py
rockgarden/output/__init__.py
rockgarden/output/builder.py
rockgarden/render/__init__.py
rockgarden/render/engine.py
rockgarden/render/markdown.py
rockgarden/templates/base.html
rockgarden/templates/folder_index.html
rockgarden/templates/page.html
rockgarden/templates/components/breadcrumbs.html
rockgarden/templates/components/nav.html
rockgarden/templates/components/theme_toggle.html
rockgarden-0.2.10.dist-info/METADATA
rockgarden-0.2.10.dist-info/WHEEL
rockgarden-0.2.10.dist-info/entry_points.txt
rockgarden-0.2.10.dist-info/RECORD
