Metadata-Version: 2.4
Name: rockgarden
Version: 0.2.10
Summary: Obsidian-compatible static site generator
Author-email: Dave Forgac <tylerdave@tylerdave.com>
License-Expression: MIT
Keywords: markdown,obsidian,static-site-generator
Classifier: Development Status :: 3 - Alpha
Classifier: Environment :: Console
Classifier: Intended Audience :: Developers
Classifier: License :: OSI Approved :: MIT License
Classifier: Programming Language :: Python :: 3.13
Classifier: Programming Language :: Python :: 3.14
Classifier: Topic :: Text Processing :: Markup :: Markdown
Requires-Python: >=3.13
Requires-Dist: jinja2>=3.1.0
Requires-Dist: linkify-it-py>=2.0.3
Requires-Dist: markdown-it-py>=3.0.0
Requires-Dist: python-frontmatter>=1.0.0
Requires-Dist: typer>=0.9.0
